[
  {"title": "Site measurement and as-built drawings", "properties": {"Task Category": {"select": "Design Iteration"}, "Project Stage": {"select": "Client Consultation and Pre-Planning"}, "Applicable Scopes": {"multi_select": ["all"]}, "Is Template": {"checkbox": true}, "Template Group": {"rich_text": "design-01"}}},
  {"title": "Brief consolidation + design direction note", "properties": {"Task Category": {"select": "Design Iteration"}, "Project Stage": {"select": "Client Consultation and Pre-Planning"}, "Applicable Scopes": {"multi_select": ["all"]}, "Is Template": {"checkbox": true}, "Template Group": {"rich_text": "design-02"}, "Depends On Groups": {"rich_text": "design-01"}}},
  {"title": "BOQ draft v1", "properties": {"Task Category": {"select": "Procurement"}, "Project Stage": {"select": "Client Consultation and Pre-Planning"}, "Applicable Scopes": {"multi_select": ["all"]}, "Is Template": {"checkbox": true}, "Template Group": {"rich_text": "boq-01"}, "Depends On Groups": {"rich_text": "design-02"}}},

  {"title": "Concept presentation to client", "properties": {"Task Category": {"select": "Client Approval"}, "Project Stage": {"select": "Design and Approvals"}, "Applicable Scopes": {"multi_select": ["all"]}, "Is Template": {"checkbox": true}, "Template Group": {"rich_text": "design-03"}, "Depends On Groups": {"rich_text": "design-02"}}},
  {"title": "Furniture layout + 3D renders v1", "properties": {"Task Category": {"select": "Design Iteration"}, "Project Stage": {"select": "Design and Approvals"}, "Applicable Scopes": {"multi_select": ["Full Home Interior", "Modular Kitchen"]}, "Is Template": {"checkbox": true}, "Template Group": {"rich_text": "design-04"}, "Depends On Groups": {"rich_text": "design-03"}}},
  {"title": "Final design + BOQ sign-off", "properties": {"Task Category": {"select": "Client Approval"}, "Project Stage": {"select": "Design and Approvals"}, "Applicable Scopes": {"multi_select": ["all"]}, "Is Template": {"checkbox": true}, "Template Group": {"rich_text": "design-05"}, "Depends On Groups": {"rich_text": "design-04,boq-01"}}},

  {"title": "Demolition (if applicable)", "properties": {"Task Category": {"select": "Civil Works"}, "Project Stage": {"select": "Flooring and Wet Areas"}, "Applicable Scopes": {"multi_select": ["Full Home Interior", "Bathroom Renovation"]}, "Is Template": {"checkbox": true}, "Template Group": {"rich_text": "civil-01"}, "Depends On Groups": {"rich_text": "design-05"}}},
  {"title": "Plumbing rough-in", "properties": {"Task Category": {"select": "MEP"}, "Project Stage": {"select": "Flooring and Wet Areas"}, "Applicable Scopes": {"multi_select": ["Full Home Interior", "Modular Kitchen", "Bathroom Renovation"]}, "Is Template": {"checkbox": true}, "Template Group": {"rich_text": "mep-01"}, "Depends On Groups": {"rich_text": "civil-01"}}},
  {"title": "Waterproofing wet areas + 24h flood test", "properties": {"Task Category": {"select": "Civil Works"}, "Project Stage": {"select": "Flooring and Wet Areas"}, "Applicable Scopes": {"multi_select": ["Full Home Interior", "Bathroom Renovation"]}, "Is Template": {"checkbox": true}, "Template Group": {"rich_text": "civil-02"}, "Depends On Groups": {"rich_text": "mep-01"}}},
  {"title": "Floor tiling / flooring install", "properties": {"Task Category": {"select": "Civil Works"}, "Project Stage": {"select": "Flooring and Wet Areas"}, "Applicable Scopes": {"multi_select": ["Full Home Interior", "Bathroom Renovation"]}, "Is Template": {"checkbox": true}, "Template Group": {"rich_text": "civil-03"}, "Depends On Groups": {"rich_text": "civil-02"}}},
  {"title": "Wall tiling in wet areas", "properties": {"Task Category": {"select": "Civil Works"}, "Project Stage": {"select": "Flooring and Wet Areas"}, "Applicable Scopes": {"multi_select": ["Full Home Interior", "Bathroom Renovation"]}, "Is Template": {"checkbox": true}, "Template Group": {"rich_text": "civil-04"}, "Depends On Groups": {"rich_text": "civil-03"}}},

  {"title": "Electrical rough-in", "properties": {"Task Category": {"select": "MEP"}, "Project Stage": {"select": "Ceiling and Wall Finishes"}, "Applicable Scopes": {"multi_select": ["all"]}, "Is Template": {"checkbox": true}, "Template Group": {"rich_text": "mep-02"}, "Depends On Groups": {"rich_text": "civil-04"}}},
  {"title": "False ceiling framing + boarding", "properties": {"Task Category": {"select": "Civil Works"}, "Project Stage": {"select": "Ceiling and Wall Finishes"}, "Applicable Scopes": {"multi_select": ["Full Home Interior", "Modular Kitchen"]}, "Is Template": {"checkbox": true}, "Template Group": {"rich_text": "civil-05"}, "Depends On Groups": {"rich_text": "mep-02"}}},
  {"title": "Wall finishes — putty + primer + paint", "properties": {"Task Category": {"select": "Civil Works"}, "Project Stage": {"select": "Ceiling and Wall Finishes"}, "Applicable Scopes": {"multi_select": ["all"]}, "Is Template": {"checkbox": true}, "Template Group": {"rich_text": "civil-06"}, "Depends On Groups": {"rich_text": "civil-05"}}},

  {"title": "Modular kitchen carcass install", "properties": {"Task Category": {"select": "Carpentry"}, "Project Stage": {"select": "Carpentry and Fixed Elements"}, "Applicable Scopes": {"multi_select": ["Full Home Interior", "Modular Kitchen", "Carpentry & FF&E"]}, "Is Template": {"checkbox": true}, "Template Group": {"rich_text": "carp-01"}, "Depends On Groups": {"rich_text": "civil-06"}}},
  {"title": "Wardrobe carcass install", "properties": {"Task Category": {"select": "Carpentry"}, "Project Stage": {"select": "Carpentry and Fixed Elements"}, "Applicable Scopes": {"multi_select": ["Full Home Interior", "Carpentry & FF&E"]}, "Is Template": {"checkbox": true}, "Template Group": {"rich_text": "carp-02"}, "Depends On Groups": {"rich_text": "civil-06"}}},
  {"title": "Kitchen shutters + handles install", "properties": {"Task Category": {"select": "Carpentry"}, "Project Stage": {"select": "Carpentry and Fixed Elements"}, "Applicable Scopes": {"multi_select": ["Full Home Interior", "Modular Kitchen", "Carpentry & FF&E"]}, "Is Template": {"checkbox": true}, "Template Group": {"rich_text": "carp-03"}, "Depends On Groups": {"rich_text": "carp-01"}}},
  {"title": "Wardrobe shutters + drawers install", "properties": {"Task Category": {"select": "Carpentry"}, "Project Stage": {"select": "Carpentry and Fixed Elements"}, "Applicable Scopes": {"multi_select": ["Full Home Interior", "Carpentry & FF&E"]}, "Is Template": {"checkbox": true}, "Template Group": {"rich_text": "carp-04"}, "Depends On Groups": {"rich_text": "carp-02"}}},

  {"title": "Furniture delivery + placement", "properties": {"Task Category": {"select": "Procurement"}, "Project Stage": {"select": "Furniture and Soft Furnishings"}, "Applicable Scopes": {"multi_select": ["Full Home Interior", "Carpentry & FF&E"]}, "Is Template": {"checkbox": true}, "Template Group": {"rich_text": "ff-01"}, "Depends On Groups": {"rich_text": "carp-03,carp-04"}}},
  {"title": "Soft furnishings install (curtains, rugs, cushions)", "properties": {"Task Category": {"select": "Procurement"}, "Project Stage": {"select": "Furniture and Soft Furnishings"}, "Applicable Scopes": {"multi_select": ["Full Home Interior", "Carpentry & FF&E"]}, "Is Template": {"checkbox": true}, "Template Group": {"rich_text": "ff-02"}, "Depends On Groups": {"rich_text": "ff-01"}}},

  {"title": "Light fixtures + dimmers final install", "properties": {"Task Category": {"select": "MEP"}, "Project Stage": {"select": "Final Touches and Styling"}, "Applicable Scopes": {"multi_select": ["all"]}, "Is Template": {"checkbox": true}, "Template Group": {"rich_text": "mep-03"}, "Depends On Groups": {"rich_text": "ff-01"}}},
  {"title": "Art + accessories styling", "properties": {"Task Category": {"select": "Procurement"}, "Project Stage": {"select": "Final Touches and Styling"}, "Applicable Scopes": {"multi_select": ["Full Home Interior", "Carpentry & FF&E"]}, "Is Template": {"checkbox": true}, "Template Group": {"rich_text": "ff-03"}, "Depends On Groups": {"rich_text": "ff-02"}}},
  {"title": "Snag list capture + fixes", "properties": {"Task Category": {"select": "Snagging"}, "Project Stage": {"select": "Final Touches and Styling"}, "Applicable Scopes": {"multi_select": ["all"]}, "Is Template": {"checkbox": true}, "Template Group": {"rich_text": "snag-01"}, "Depends On Groups": {"rich_text": "mep-03,ff-02"}}},

  {"title": "Site cleaning + final styling shoot", "properties": {"Task Category": {"select": "Handover"}, "Project Stage": {"select": "Handover"}, "Applicable Scopes": {"multi_select": ["all"]}, "Is Template": {"checkbox": true}, "Template Group": {"rich_text": "ho-01"}, "Depends On Groups": {"rich_text": "snag-01"}}},
  {"title": "Handover checklist walkthrough with client", "properties": {"Task Category": {"select": "Handover"}, "Project Stage": {"select": "Handover"}, "Applicable Scopes": {"multi_select": ["all"]}, "Is Template": {"checkbox": true}, "Template Group": {"rich_text": "ho-02"}, "Depends On Groups": {"rich_text": "ho-01"}}},
  {"title": "Final invoice + client sign-off", "properties": {"Task Category": {"select": "Handover"}, "Project Stage": {"select": "Handover"}, "Applicable Scopes": {"multi_select": ["all"]}, "Is Template": {"checkbox": true}, "Template Group": {"rich_text": "ho-03"}, "Depends On Groups": {"rich_text": "ho-02"}}}
]
